lophat-0.9.2.dist-info/METADATA
lophat-0.9.2.dist-info/WHEEL
lophat-0.9.2.dist-info/license_files/LICENSE
lophat/__init__.py
lophat/__init__.pyi
lophat/py.typed
lophat/lophat.cpython-311-x86_64-linux-gnu.so
lophat-0.9.2.dist-info/RECORD
