Metadata-Version: 2.1
Name: lophat
Version: 0.9.2
Classifier: Programming Language :: Rust
Classifier: Programming Language :: Python :: Implementation :: CPython
Classifier: Programming Language :: Python :: Implementation :: PyPy
License-File: LICENSE
Summary: Lockfree Persistent Homology Algorithm Toolbox
Home-Page: https://github.com/tomchaplin/lophat
License: MIT
Requires-Python: >=3.7
Project-URL: Source Code, https://github.com/tomchaplin/lophat
